<?xml version="1.0" encoding="UTF-8"?>
<Defs>
	
	<!--===== Survival Meal =====-->
	<RecipeDef Name="RJW_Gastronomy_SurvivalMealBase" ParentName="RJW_Gastronomy_Base_Recipe" Abstract="True">
		<researchPrerequisite>PackagedSurvivalMeal</researchPrerequisite>
		<skillRequirements>
			<Cooking>8</Cooking>
		</skillRequirements>
	</RecipeDef>

	<RecipeDef ParentName="RJW_Gastronomy_SurvivalMealBase">
		<defName>RJW_Gastronomy_SurvivalMealSingle</defName>
		<description>Prepare a packaged survival meal from a combination of various erotic ingredients. Some of the ingredients are wasted.</description>
		<jobString>Cooking erotic survival meal</jobString>
		<label>cook erotic packaged survival meal</label>
		<displayPriority>15</displayPriority>
		<ingredients>
		<li>
			<filter>
				<categories>
					<li>RJW_Gastronomy_Humilk</li>
					<li>MeatRaw</li>
				</categories>
			</filter>
			<count>0.30</count>
		</li>
		<li>
			<filter>
				<categories>
					<li>RJW_Gastronomy_FoodRaw</li>
				</categories>
				<disallowedCategories>
					<li>MeatRaw</li>
					<li>RJW_Gastronomy_Humilk</li>
				</disallowedCategories>
			</filter>
			<count>0.30</count>
		</li>
		</ingredients>
		<workAmount>500</workAmount>
		<products>
			<RJW_Gastronomy_MealSurvivalPack>1</RJW_Gastronomy_MealSurvivalPack>
		</products>
	</RecipeDef>

	<RecipeDef ParentName="RJW_Gastronomy_SurvivalMealBase">
		<defName>RJW_Gastronomy_SurvivalMealBulk</defName>
		<description>Prepare a packaged survival meal from a combination of various erotic ingredients. Some of the ingredients are wasted.</description>
		<jobString>Cooking erotic survival meals x4</jobString>
		<label>cook erotic packaged survival meal x4</label>
		<displayPriority>15</displayPriority>
		<ingredients>
		<li>
			<filter>
				<categories>
					<li>RJW_Gastronomy_Humilk</li>
					<li>MeatRaw</li>
				</categories>
			</filter>
			<count>1.2</count>
		</li>
		<li>
			<filter>
				<categories>
					<li>RJW_Gastronomy_FoodRaw</li>
				</categories>
				<disallowedCategories>
					<li>MeatRaw</li>
					<li>RJW_Gastronomy_Humilk</li>
				</disallowedCategories>
			</filter>
			<count>1.2</count>
		</li>
		</ingredients>
		<workAmount>1000</workAmount>
		<products>
			<RJW_Gastronomy_MealSurvivalPack>4</RJW_Gastronomy_MealSurvivalPack>
		</products>
	</RecipeDef>

	<!--===== Simple =====-->
	<RecipeDef ParentName="RJW_Gastronomy_Base_Recipe">
		<defName>Cook_Erotic_Meal_Simple</defName>
		<label>cook erotic simple meal</label>
		<description>Cook a straightforward erotic meal from one ingredient.</description>
		<jobString>Cooking erotic simple meal.</jobString>
		<displayPriority>10</displayPriority>
		<ingredients>
		<li>
			<filter>
				<categories>
					<li>RJW_Gastronomy_FoodRaw</li>
				</categories>
			</filter>
			<count>0.5</count>
		</li>
		</ingredients>
		<products>
			<RJW_Gastronomy_MealSimple>1</RJW_Gastronomy_MealSimple>
		</products>
		<workAmount>200</workAmount>
        <skillRequirements>
          <Cooking>1</Cooking>
        </skillRequirements>
	</RecipeDef>
	
	<RecipeDef ParentName="RJW_Gastronomy_Base_Recipe">
		<defName>Cook_Erotic_Meal_Simple_Bulk</defName>
		<label>cook erotic simple meal x4</label>
		<description>Cook a batch of straightforward erotic meals from one ingredient.</description>
		<jobString>Cooking erotic simple meals x4.</jobString>
		<displayPriority>10</displayPriority>
		<ingredients>
		<li>
			<filter>
				<categories>
					<li>RJW_Gastronomy_FoodRaw</li>
				</categories>
			</filter>
			<count>2</count>
		</li>
		</ingredients>
		<products>
			<RJW_Gastronomy_MealSimple>4</RJW_Gastronomy_MealSimple>
		</products>
		<workAmount>400</workAmount>
        <skillRequirements>
          <Cooking>1</Cooking>
        </skillRequirements>
	</RecipeDef>

	<!-- ===== Fine ===== -->
	<RecipeDef ParentName="RJW_Gastronomy_Base_Recipe">
		<defName>Cook_Erotic_Meal_Fine_Single</defName>
		<label>cook erotic fine meal</label>
		<description>Cook a complex meal from a combination of various erotic ingredients.</description>
		<jobString>Cooking erotic fine meal.</jobString>
		<displayPriority>11</displayPriority>
		<skillRequirements>
			<Cooking>6</Cooking>
		</skillRequirements>
		<ingredients>
			<li>
				<filter>
					<categories>
						<li>RJW_Gastronomy_Humilk</li>
						<li>MeatRaw</li>
					</categories>
				</filter>
				<count>0.25</count>
			</li>
			<li>
				<filter>
					<categories>
						<li>RJW_Gastronomy_FoodRaw</li>
					</categories>
					<disallowedCategories>
						<li>MeatRaw</li>
						<li>RJW_Gastronomy_Humilk</li>
					</disallowedCategories>
				</filter>
				<count>0.25</count>
			</li>
		</ingredients>
		<workAmount>450</workAmount>
		<products>
			<RJW_Gastronomy_MealFine>1</RJW_Gastronomy_MealFine>
		</products>
	</RecipeDef>

	<RecipeDef ParentName="RJW_Gastronomy_Base_Recipe">
		<defName>Cook_Erotic_Meal_Fine_Bulk</defName>
		<label>cook erotic fine meal x4</label>
		<description>Cook 4 complex meals from a combination of various erotic ingredients.</description>
		<jobString>Cooking erotic fine meals x4.</jobString>
		<displayPriority>11</displayPriority>
		<skillRequirements>
			<Cooking>6</Cooking>
		</skillRequirements>
		<ingredients>
			<li>
				<filter>
					<categories>
						<li>RJW_Gastronomy_Humilk</li>
						<li>MeatRaw</li>
					</categories>
				</filter>
				<count>1</count>
			</li>
			<li>
				<filter>
					<categories>
						<li>RJW_Gastronomy_FoodRaw</li>
					</categories>
					<disallowedCategories>
						<li>MeatRaw</li>
						<li>RJW_Gastronomy_Humilk</li>
					</disallowedCategories>
				</filter>
				<count>1</count>
			</li>
		</ingredients>
		<workAmount>900</workAmount>
		<products>
			<RJW_Gastronomy_MealFine>4</RJW_Gastronomy_MealFine>
		</products>
	</RecipeDef>

	<!-- ===== Lavish ===== -->
	<RecipeDef ParentName="RJW_Gastronomy_Base_Recipe">
		<defName>Cook_Erotic_Meal_Lavish_Single</defName>
		<label>cook erotic lavish meal</label>
		<description>Cook a very complex erotic meal from a combination of various ingredients. Much of the ingredients are wasted in order to create better eating experience.</description>
		<jobString>Cooking erotic lavish meal.</jobString>
		<displayPriority>12</displayPriority>
		<skillRequirements>
			<Cooking>8</Cooking>
		</skillRequirements>
		<ingredients>
			<li>
				<filter>
					<categories>
						<li>RJW_Gastronomy_Humilk</li>
						<li>MeatRaw</li>
					</categories>
				</filter>
				<count>0.5</count>
			</li>
			<li>
				<filter>
					<categories>
						<li>RJW_Gastronomy_FoodRaw</li>
					</categories>
					<disallowedCategories>
						<li>MeatRaw</li>
						<li>RJW_Gastronomy_Humilk</li>
					</disallowedCategories>
				</filter>
				<count>0.5</count>
			</li>
		</ingredients>
		<workAmount>800</workAmount>
		<products>
			<RJW_Gastronomy_MealLavish>1</RJW_Gastronomy_MealLavish>
		</products>
	</RecipeDef>

	<RecipeDef ParentName="RJW_Gastronomy_Base_Recipe">
		<defName>Cook_Erotic_Meal_Lavish_Bulk</defName>
		<label>cook erotic lavish meal x4</label>
		<description>Cook very complex erotic meals from a combination of various ingredients. Much of the ingredients are wasted in order to create better eating experience.</description>
		<jobString>Cooking erotic lavish meals x4.</jobString>
		<displayPriority>12</displayPriority>
		<ingredients>
			<li>
				<filter>
					<categories>
						<li>RJW_Gastronomy_Humilk</li>
						<li>MeatRaw</li>
					</categories>
				</filter>
				<count>2</count>
			</li>
			<li>
				<filter>
					<categories>
						<li>RJW_Gastronomy_FoodRaw</li>
					</categories>
					<disallowedCategories>
						<li>MeatRaw</li>
						<li>RJW_Gastronomy_Humilk</li>
					</disallowedCategories>
				</filter>
				<count>2</count>
			</li>
		</ingredients>
		<workAmount>1600</workAmount>
		<products>
			<RJW_Gastronomy_MealLavish>4</RJW_Gastronomy_MealLavish>
		</products>
	</RecipeDef>

	<!-- ===== Gourmet ===== -->
	<RecipeDef Name="RJW_Gastronomy_Base_Recipe_Gourmet" ParentName="RJW_Gastronomy_Base_Recipe" Abstract="True">
		<!-- VCE custom ingredientValueGetterClass -->
		<!-- If non ingestable or condiment, use flat amount -->
		<!--<ingredientValueGetterClass MayRequire="vanillaexpanded.vcooke">VanillaCookingExpanded.IngredientValueGetter_NutritionWithExtraIngredient</ingredientValueGetterClass>-->
		<description>Cook a culinary work of art, elevating the taste of each ingredient to the peak, with refined, even elaborate preparation and presentation of an aesthetic and balanced meal. Most of the ingredients are discarded, leaving only the best of the best.</description>
		<displayPriority>13</displayPriority>
		<skillRequirements>
			<Cooking>10</Cooking>
		</skillRequirements>
		<fixedIngredientFilter>
			<categories>
			<li MayRequire="vanillaexpanded.vcooke">VCE_Condiments</li>
			</categories>
		</fixedIngredientFilter>
		<defaultIngredientFilter>
			<categories>
			<li MayRequire="vanillaexpanded.vcooke">VCE_Condiments</li>
			</categories>
		</defaultIngredientFilter>
	</RecipeDef>

	<RecipeDef ParentName="RJW_Gastronomy_Base_Recipe_Gourmet">
		<defName>Cook_Erotic_Meal_Gourmet_Single</defName>
		<label>cook erotic gourmet meal</label>
		<jobString>Cooking erotic gourmet meal.</jobString>
		<ingredients>
			<li>
				<filter>
					<categories>
						<li>RJW_Gastronomy_Humilk</li>
						<li>MeatRaw</li>
					</categories>
				</filter>
				<count>0.75</count>
			</li>
			<li>
				<filter>
					<categories>
						<li>RJW_Gastronomy_FoodRaw</li>
					</categories>
					<disallowedCategories>
						<li>MeatRaw</li>
						<li>RJW_Gastronomy_Humilk</li>
					</disallowedCategories>
				</filter>
				<count>0.75</count>
			</li>
			<li MayRequire="vanillaexpanded.vcooke">
				<filter>
					<categories>
						<li>VCE_Condiments</li>
					</categories>
				</filter>
				<!-- Flat amount -->
				<count>1</count>
			</li>
		</ingredients>
		<workAmount>1000</workAmount>
		<products>
			<RJW_Gastronomy_MealGourmet>1</RJW_Gastronomy_MealGourmet>
		</products>
	</RecipeDef>

	<RecipeDef ParentName="RJW_Gastronomy_Base_Recipe_Gourmet">
		<defName>Cook_Erotic_Meal_Gourmet_Bulk</defName>
		<label>cook erotic gourmet meal x4</label>
		<jobString>Cooking erotic gourmet meal x4.</jobString>
		<ingredients>
			<li>
				<filter>
					<categories>
						<li>RJW_Gastronomy_Humilk</li>
						<li>MeatRaw</li>
					</categories>
				</filter>
				<count>3</count>
			</li>
			<li>
				<filter>
					<categories>
						<li>RJW_Gastronomy_FoodRaw</li>
					</categories>
					<disallowedCategories>
						<li>MeatRaw</li>
						<li>RJW_Gastronomy_Humilk</li>
					</disallowedCategories>
				</filter>
				<count>3</count>
			</li>
			<li MayRequire="vanillaexpanded.vcooke">
				<filter>
					<categories>
						<li>VCE_Condiments</li>
					</categories>
				</filter>
				<!-- Flat amount -->
				<count>4</count>
			</li>
		</ingredients>
		<workAmount>3000</workAmount>
		<products>
			<RJW_Gastronomy_MealGourmet>4</RJW_Gastronomy_MealGourmet>
		</products>
	</RecipeDef>

</Defs>